theiaengine/__init__.py
theiaengine/utils/request_collections.py
theiaengine/utils/response_collections.py
theiaengine-2023.7.1.dist-info/WHEEL
theiaengine-2023.7.1.dist-info/METADATA
theiaengine-2023.7.1.dist-info/RECORD
